pooling/__init__.py
pooling/base.py
pooling/mysql.py
pooling-0.1.12.dist-info/licenses/LICENSE
pooling-0.1.12.dist-info/METADATA
pooling-0.1.12.dist-info/WHEEL
pooling-0.1.12.dist-info/top_level.txt
pooling-0.1.12.dist-info/RECORD
